pydantic_evals/__init__.py
pydantic_evals/version.py
pydantic_evals/common/typing.py
pydantic_evals/metrics/__init__.py
pydantic_evals/metrics/base.py
pydantic_evals/metrics/evaluator.py
structured_evals-0.0.0.dev0.dist-info/LICENSE
structured_evals-0.0.0.dev0.dist-info/METADATA
structured_evals-0.0.0.dev0.dist-info/WHEEL
structured_evals-0.0.0.dev0.dist-info/top_level.txt
structured_evals-0.0.0.dev0.dist-info/RECORD
