Metadata-Version: 2.2
Name: structured-evals
Version: 0.0.0.dev0
Summary: Evals framework for evaluating LLMs with structured outputs (i.e. JSON-mode)
Author-email: VLM Support <support@vlm.com>
License: Apache-2.0
Classifier: Development Status :: 4 - Beta
Classifier: Programming Language :: Python
Classifier: Environment :: Console
Classifier: Intended Audience :: Developers
Classifier: Intended Audience :: Education
Classifier: Intended Audience :: Information Technology
Classifier: Intended Audience :: Science/Research
Classifier: Topic :: Software Development :: Libraries
Classifier: Topic :: Scientific/Engineering :: Artificial Intelligence
Classifier: License :: OSI Approved :: Apache Software License
Classifier: Operating System :: POSIX :: Linux
Classifier: Operating System :: MacOS
Classifier: Programming Language :: Python :: 3 :: Only
Classifier: Programming Language :: Python :: 3.9
Classifier: Programming Language :: Python :: 3.10
Classifier: Programming Language :: Python :: 3.11
Classifier: Programming Language :: Python :: 3.12
Requires-Python: >=3.9
License-File: LICENSE
Requires-Dist: pydantic>=2.0.0
Requires-Dist: pandas>=1.3.0
Requires-Dist: loguru>=0.6.0
Requires-Dist: rich>=12.0.0
Provides-Extra: test
Requires-Dist: pytest; extra == "test"
Provides-Extra: build
Requires-Dist: twine; extra == "build"
Requires-Dist: build; extra == "build"
Provides-Extra: all
